clouditia_manager/__init__.py
clouditia_manager/client.py
clouditia_manager/exceptions.py
clouditia_manager-1.8.0.dist-info/METADATA
clouditia_manager-1.8.0.dist-info/WHEEL
clouditia_manager-1.8.0.dist-info/top_level.txt
clouditia_manager-1.8.0.dist-info/RECORD
