Metadata-Version: 2.4
Name: clouditia-manager
Version: 1.8.0
Summary: Manage GPU sessions on Clouditia platform
Home-page: https://clouditia.com
Author: Aina KIKI-SAGBE
Author-email: support@clouditia.com
Maintainer: Aina KIKI-SAGBE
Maintainer-email: support@clouditia.com
License: MIT
Project-URL: Documentation, https://clouditia.com/docs/manager-sdk
Project-URL: Bug Reports, https://github.com/clouditia/clouditia-manager/issues
Project-URL: Source, https://github.com/clouditia/clouditia-manager
Keywords: gpu cloud remote-execution machine-learning deep-learning pytorch tensorflow cuda jupyter api
Classifier: Development Status :: 4 - Beta
Classifier: Intended Audience :: Developers
Classifier: License :: OSI Approved :: MIT License
Classifier: Operating System :: OS Independent
Classifier: Programming Language :: Python :: 3
Classifier: Programming Language :: Python :: 3.10
Classifier: Programming Language :: Python :: 3.11
Classifier: Programming Language :: Python :: 3.12
Classifier: Topic :: Software Development :: Libraries :: Python Modules
Classifier: Topic :: Scientific/Engineering :: Artificial Intelligence
Requires-Python: >=3.10
Requires-Dist: requests>=2.25.0
Provides-Extra: s3
Requires-Dist: boto3>=1.26.0; extra == "s3"
Dynamic: author
Dynamic: author-email
Dynamic: classifier
Dynamic: description
Dynamic: description-content-type
Dynamic: home-page
Dynamic: keywords
Dynamic: license
Dynamic: maintainer
Dynamic: maintainer-email
Dynamic: project-url
Dynamic: provides-extra
Dynamic: requires-dist
Dynamic: requires-python
Dynamic: summary
